{
    "Premier": "ball_templates/premier.png", 
    "Poke": "ball_templates/poke.png",
    "Great": "ball_templates/great.png",
    "Ultra": "ball_templates/ultra.png",
    "Friend": "ball_templates/friend.png",
    "Cherish": "ball_templates/cherish.png",
    "Moon": "ball_templates/moon.png",
    "Love": "ball_templates/love.png",
    "Beast": "ball_templates/beast.png",
    "Dive": "ball_templates/dive.png",
    "Dream": "ball_templates/dream.png",
    "Dusk": "ball_templates/dusk.png",
    "Fast": "ball_templates/fast.png",
    "Heal": "ball_templates/heal.png",
    "Heavy": "ball_templates/heavy.png",
    "Level": "ball_templates/level.png",
    "Lure": "ball_templates/lure.png",
    "Luxury": "ball_templates/luxury.png",
    "Master": "ball_templates/master.png",
    "Nest": "ball_templates/nest.png",
    "Net": "ball_templates/net.png",
    "Quick": "ball_templates/quick.png",
    "Repeat": "ball_templates/repeat.png",
    "Safari": "ball_templates/safari.png",
    "Sport": "ball_templates/sport.png",
    "Timer": "ball_templates/timer.png",
    "Strange": "ball_templates/strange.png",
    "APoke": "ball_templates/apoke.png",
    "AGreat": "ball_templates/agreat.png",
    "AUltra": "ball_templates/aultra.png",
    "AOrigin": "ball_templates/aorigin.png",
    "AFeather": "ball_templates/afeather.png",
    "AWing": "ball_templates/awing.png",
    "AJet": "ball_templates/ajet.png",
    "AHeavy": "ball_templates/aheavy.png",
    "ALeaden": "ball_templates/aleaden.png",
    "AGigaton": "ball_templates/agigaton.png"
}